README.md
setup.py
pytorch_tdnn/__init__.py
pytorch_tdnn/tdnn.py
pytorch_tdnn/tdnnf.py
pytorch_tdnn.egg-info/PKG-INFO
pytorch_tdnn.egg-info/SOURCES.txt
pytorch_tdnn.egg-info/dependency_links.txt
pytorch_tdnn.egg-info/requires.txt
pytorch_tdnn.egg-info/top_level.txt