Metadata-Version: 2.1
Name: pytorch-tdnn
Version: 1.0.0
Summary: TDNN and TDNN-F layers in PyTorch
Home-page: https://github.com/desh2608/pytorch-tdnn
Author: Desh Raj
Author-email: r.desh26@gmail.com
License: Apache 2.0
Keywords: speech recognition,time delay neural networks,factored TDNN,acoustic modeling
Platform: UNKNOWN
Classifier: Development Status :: 4 - Beta
Classifier: Intended Audience :: Developers
Classifier: Topic :: Scientific/Engineering :: Artificial Intelligence
Classifier: License :: OSI Approved :: MIT License
Classifier: Programming Language :: Python :: 3.6
